[
  {
    "username": "emily.sinclair",
    "fullName": "Emily Sinclair",
    "email": "emily.sinclair@example.com",
    "password": "password123",
    "biography": "Passionate poet and nature lover.",
    "socialNetworks": {
      "twitter": "emily_sinclair",
      "instagram": "emily.poet"
    }
  },
  {
    "username": "luna.parker",
    "fullName": "Luna Parker",
    "email": "luna.parker@example.com",
    "password": "password456",
    "biography": "Capturing emotions through words.",
    "socialNetworks": {
      "twitter": "luna_writes",
      "instagram": "luna.writes"
    }
  },
  {
    "username": "victor.anderson",
    "fullName": "Victor Anderson",
    "email": "victor.anderson@example.com",
    "password": "password789",
    "biography": "Exploring the realms of imagination.",
    "socialNetworks": {
      "twitter": "victor_writes",
      "instagram": "victor.writes"
    }
  },
  {
    "username": "amara.williams",
    "fullName": "Amara Williams",
    "email": "amara.williams@example.com",
    "password": "password987",
    "biography": "Dancing with words in the realm of poetry.",
    "socialNetworks": {
      "twitter": "amara_poet",
      "instagram": "amara.poet"
    }
  },
  {
    "username": "oliver.thompson",
    "fullName": "Oliver Thompson",
    "email": "oliver.thompson@example.com",
    "password": "password654",
    "biography": "Painting emotions with the strokes of poetry.",
    "socialNetworks": {
      "twitter": "oliver_writes",
      "instagram": "oliver.writes"
    }
  },
  {
    "username": "sophia.roberts",
    "fullName": "Sophia Roberts",
    "email": "sophia.roberts@example.com",
    "password": "password321",
    "biography": "Weaving tales of love and dreams.",
    "socialNetworks": {
      "twitter": "sophia_poet",
      "instagram": "sophia.poet"
    }
  },
  {
    "username": "gabriel.adams",
    "fullName": "Gabriel Adams",
    "email": "gabriel.adams@example.com",
    "password": "password012",
    "biography": "Wordsmith on a journey of self-expression.",
    "socialNetworks": {
      "twitter": "gabriel_writes",
      "instagram": "gabriel.writes"
    }
  },
  {
    "username": "aria.mitchell",
    "fullName": "Aria Mitchell",
    "email": "aria.mitchell@example.com",
    "password": "password876",
    "biography": "Embracing the whispers of inspiration.",
    "socialNetworks": {
      "twitter": "aria_poet",
      "instagram": "aria.poet"
    }
  }
]
